setup.cfg
setup.py
pulse/__init__.py
pulse/middleware.py
pulse.egg-info/PKG-INFO
pulse.egg-info/SOURCES.txt
pulse.egg-info/dependency_links.txt
pulse.egg-info/entry_points.txt
pulse.egg-info/not-zip-safe
pulse.egg-info/requires.txt
pulse.egg-info/top_level.txt