Metadata-Version: 1.0
Name: pulse
Version: 0.1
Summary: Simple scheduling WSGI middleware.
Home-page: UNKNOWN
Author: Sam Rayment
Author-email: UNKNOWN
License: MIT Licence
Platform: UNKNOWN
Classifier: Topic :: Internet :: WWW/HTTP :: WSGI
